tree2structure/__init__.py
tree2structure/generator.py
tree2structure/parser.py
tree2structure-0.1.1.dist-info/METADATA
tree2structure-0.1.1.dist-info/WHEEL
tree2structure-0.1.1.dist-info/RECORD
