Metadata-Version: 2.3
Name: tree2structure
Version: 0.1.1
Summary: Convert tree-style folder structure into real files and folders with comments
License: MIT
Keywords: parser,project scaffolding,file generator
Author: Anar Dzhafarov
Author-email: a@dzhfrv.com
Requires-Python: >=3.8
Classifier: License :: OSI Approved :: MIT License
Classifier: Programming Language :: Python :: 3
Classifier: Programming Language :: Python :: 3.8
Classifier: Programming Language :: Python :: 3.9
Classifier: Programming Language :: Python :: 3.10
Classifier: Programming Language :: Python :: 3.11
Classifier: Programming Language :: Python :: 3.12
Classifier: Programming Language :: Python :: 3.13
Requires-Dist: pytest (>=8.3.5,<9.0.0)
Project-URL: Documentation, https://github.com/atvor/tree2structure#readme
Project-URL: Homepage, https://github.com/atvor/tree2structure.git
Project-URL: Repository, https://github.com/atvor/tree2structure.git
